premium_calculator/__init__.py
premium_calculator/premium_calculator.py
premium_calculator_shivangi-0.0.1.dist-info/LICENSE
premium_calculator_shivangi-0.0.1.dist-info/METADATA
premium_calculator_shivangi-0.0.1.dist-info/WHEEL
premium_calculator_shivangi-0.0.1.dist-info/top_level.txt
premium_calculator_shivangi-0.0.1.dist-info/RECORD
