Metadata-Version: 2.1
Name: premium_calculator_shivangi
Version: 0.0.1
Summary: This is a premium calculator
Home-page: https://github.com/pypa/sampleproject
Author: shivangi
Author-email: Shivangi <shivangipandeydt.126@gmail.com>
Project-URL: Homepage, https://github.com/pypa/sampleproject
Project-URL: Issues, https://github.com/pypa/sampleproject/issues
Classifier: Programming Language :: Python :: 3
Classifier: License :: OSI Approved :: MIT License
Classifier: Operating System :: OS Independent
Requires-Python: >=3.6
License-File: LICENSE
